<?xml version="1.0" encoding="UTF-8"?>
<!DOCTYPE mapper PUBLIC "-//mybatis.org//DTD Mapper 3.0//EN"
    "http://mybatis.org/dtd/mybatis-3-mapper.dtd">
<mapper namespace="kr.go.molit.icas.er.rprt.acft.ErAcftFuelMapper">

    <!-- ════════════════════════════════════════════
         공통 컬럼 목록
         ════════════════════════════════════════════ -->
    <sql id="acftFuelColumns">
        f.er_id,
        f.acft_sn,
        f.acft_type_cd,
        f.regis_mark,
        f.ownr_ls_se_cd,
        f.fuel_type_cd,
        f.dnsty_se_cd,
        f.use_bgng_dt,
        f.use_end_dt,
        f.frst_reg_dt,
        f.frst_reg_user_id,
        f.last_chg_dt,
        f.last_chg_user_id
    </sql>

    <!-- ════════════════════════════════════════════
         목록 조회 (acft_sn ASC, 유효구간 필터)
         ════════════════════════════════════════════ -->
    <select id="selectByErId"
            resultType="kr.go.molit.icas.er.rprt.acft.domain.ErAcftFuelVO">
        SELECT <include refid="acftFuelColumns"/>
          FROM er.tn_er_acft_fuel f
         WHERE f.er_id = #{erId}
           AND NOW() BETWEEN f.use_bgng_dt AND f.use_end_dt
         ORDER BY f.acft_sn ASC
    </select>

    <!-- ════════════════════════════════════════════
         단건 조회 (복합 PK)
         ════════════════════════════════════════════ -->
    <select id="selectOne"
            resultType="kr.go.molit.icas.er.rprt.acft.domain.ErAcftFuelVO">
        SELECT <include refid="acftFuelColumns"/>
          FROM er.tn_er_acft_fuel f
         WHERE f.er_id   = #{erId}
           AND f.acft_sn = #{acftSn}
           AND NOW() BETWEEN f.use_bgng_dt AND f.use_end_dt
    </select>

    <!-- ════════════════════════════════════════════
         다음 acft_sn 채번: max(acft_sn) + 1, 없으면 1
         유효구간 외 행 포함하여 sn 재사용 방지
         ════════════════════════════════════════════ -->
    <select id="selectNextSn" resultType="int">
        SELECT COALESCE(MAX(acft_sn), 0) + 1
          FROM er.tn_er_acft_fuel
         WHERE er_id = #{erId}
    </select>

    <!-- ════════════════════════════════════════════
         등록기호 중복 체크 (같은 er_id + regis_mark)
         excludeSn 은 자기 자신 제외용 (신규 시 0 전달)
         ════════════════════════════════════════════ -->
    <select id="existsByRegisMark" resultType="boolean">
        SELECT CASE WHEN COUNT(*) > 0 THEN TRUE ELSE FALSE END
          FROM er.tn_er_acft_fuel
         WHERE er_id      = #{erId}
           AND regis_mark = #{regisMark}
           AND acft_sn   != #{excludeSn}
           AND NOW() BETWEEN use_bgng_dt AND use_end_dt
    </select>

    <!-- ════════════════════════════════════════════
         신규 등록
         ════════════════════════════════════════════ -->
    <insert id="insertAcftFuel"
            parameterType="kr.go.molit.icas.er.rprt.acft.domain.ErAcftFuelVO">
        INSERT INTO er.tn_er_acft_fuel
            (er_id, acft_sn, acft_type_cd, regis_mark, ownr_ls_se_cd,
             fuel_type_cd, dnsty_se_cd,
             use_bgng_dt, use_end_dt,
             frst_reg_dt, frst_reg_user_id,
             last_chg_dt, last_chg_user_id)
        VALUES
            (#{erId}, #{acftSn}, #{acftTypeCd}, #{regisMark}, #{ownrLsSeCd},
             #{fuelTypeCd}, #{dnstySecCd},
             NOW(), '9999-12-31 23:59:59',
             NOW(), #{frstRegUserId},
             NOW(), #{lastChgUserId})
    </insert>

    <!-- ════════════════════════════════════════════
         수정 (유효구간 필터 포함)
         ════════════════════════════════════════════ -->
    <update id="updateAcftFuel"
            parameterType="kr.go.molit.icas.er.rprt.acft.domain.ErAcftFuelVO">
        UPDATE er.tn_er_acft_fuel
           SET acft_type_cd      = #{acftTypeCd},
               regis_mark        = #{regisMark},
               ownr_ls_se_cd     = #{ownrLsSeCd},
               fuel_type_cd      = #{fuelTypeCd},
               dnsty_se_cd       = #{dnstySecCd},
               last_chg_dt       = NOW(),
               last_chg_user_id  = #{lastChgUserId}
         WHERE er_id   = #{erId}
           AND acft_sn = #{acftSn}
           AND NOW() BETWEEN use_bgng_dt AND use_end_dt
    </update>

    <!-- ════════════════════════════════════════════
         소프트삭제: use_end_dt = NOW() - 1분
         ════════════════════════════════════════════ -->
    <update id="softDeleteOne">
        UPDATE er.tn_er_acft_fuel
           SET use_end_dt        = NOW() - INTERVAL '1 minute',
               last_chg_dt       = NOW(),
               last_chg_user_id  = #{userId}
         WHERE er_id   = #{erId}
           AND acft_sn = #{acftSn}
           AND NOW() BETWEEN use_bgng_dt AND use_end_dt
    </update>

    <!-- ════════════════════════════════════════════
         신버전 ER 복사: src → dst (INSERT ... SELECT)
         ════════════════════════════════════════════ -->
    <insert id="copyToNewEr">
        INSERT INTO er.tn_er_acft_fuel
            (er_id, acft_sn, acft_type_cd, regis_mark, ownr_ls_se_cd,
             fuel_type_cd, dnsty_se_cd,
             use_bgng_dt, use_end_dt,
             frst_reg_dt, frst_reg_user_id,
             last_chg_dt, last_chg_user_id)
        SELECT #{dstErId}, acft_sn, acft_type_cd, regis_mark, ownr_ls_se_cd,
               fuel_type_cd, dnsty_se_cd,
               NOW(), '9999-12-31 23:59:59',
               NOW(), #{userId},
               NOW(), #{userId}
          FROM er.tn_er_acft_fuel
         WHERE er_id = #{srcErId}
           AND NOW() BETWEEN use_bgng_dt AND use_end_dt
    </insert>

</mapper>
